tkitbilstm/__init__.py
tkitbilstm/bilstm.py
tkitbilstm-0.0.0.1.3.dist-info/LICENSE
tkitbilstm-0.0.0.1.3.dist-info/METADATA
tkitbilstm-0.0.0.1.3.dist-info/WHEEL
tkitbilstm-0.0.0.1.3.dist-info/top_level.txt
tkitbilstm-0.0.0.1.3.dist-info/RECORD
